temperate/__init__.py
temperate/cli.py
temperate/utils.py
temperate/wiser.py
temperate-0.0.1.dist-info/LICENSE
temperate-0.0.1.dist-info/METADATA
temperate-0.0.1.dist-info/WHEEL
temperate-0.0.1.dist-info/entry_points.txt
temperate-0.0.1.dist-info/top_level.txt
temperate-0.0.1.dist-info/RECORD
